{"type":"result","timestamp":"2024-09-14T06:31:26Z","ping":{"jitter":48.353,"latency":257.079,"low":174.753,"high":352.820},"download":{"bandwidth":178825,"bytes":1839984,"elapsed":13012,"latency":{"iqm":2192.133,"low":400.468,"high":3864.890,"jitter":103.172}},"upload":{"bandwidth":51073,"bytes":635104,"elapsed":13578},"packetLoss":10.894941634241246,"isp":"Universitas Sebelas Maret","interface":{"internalIp":"192.168.1.196","name":"sta17-wlan0","macAddr":"02:00:00:00:10:00","isVpn":false,"externalIp":"203.6.148.253"},"server":{"id":13825,"host":"speedtestsrk1.gmedia.net.id","port":8080,"name":"GMEDIA","location":"Surakarta","country":"Indonesia","ip":"49.128.181.12"},"result":{"id":"63e2e203-cb85-485d-a19f-0f54059b8f01","url":"https://www.speedtest.net/result/c/63e2e203-cb85-485d-a19f-0f54059b8f01","persisted":true}}
