{
    "type": "result",
    "timestamp": "2024-09-15T08:23:16Z",
    "ping": {
        "jitter": 4.46,
        "latency": 33.348,
        "low": 27.027,
        "high": 36.642
    },
    "download": {
        "bandwidth": 146648,
        "bytes": 1931799,
        "elapsed": 11801,
        "latency": {
            "iqm": 364.49,
            "low": 30.594,
            "high": 1146.147,
            "jitter": 76.762
        }
    },
    "upload": {
        "bandwidth": 58661,
        "bytes": 793168,
        "elapsed": 14993,
        "latency": {
            "iqm": 274.61,
            "low": 26.142,
            "high": 1253.379,
            "jitter": 69.768
        }
    },
    "packetLoss": 13.478260869565217,
    "isp": "Universitas Sebelas Maret",
    "interface": {
        "internalIp": "192.168.1.193",
        "name": "sta20-wlan0",
        "macAddr": "02:00:00:00:13:00",
        "isVpn": false,
        "externalIp": "203.6.148.253"
    },
    "server": {
        "id": 36813,
        "host": "speedtest2.solo.citra.net.id",
        "port": 8080,
        "name": "CitraNet",
        "location": "Surakarta",
        "country": "Indonesia",
        "ip": "202.65.123.22"
    },
    "result": {
        "id": "55b2a94d-7fb9-4778-9489-498760ebc09b",
        "url": "https://www.speedtest.net/result/c/55b2a94d-7fb9-4778-9489-498760ebc09b",
        "persisted": true
    }
}